Metadata-Version: 2.1
Name: Unalix
Version: 0.9
Summary: Small, dependency-free, fast Python package for removing tracking fields from URLs.
Home-page: https://github.com/AmanoTeam/Unalix
Author: SnwMds
Author-email: snwmds@tutanota.com
License: LGPL-3.0
Project-URL: Bug Tracker, https://github.com/AmanoTeam/Unalix/issues
Platform: UNKNOWN
Classifier: License :: OSI Approved :: GNU Lesser General Public License v3 (LGPLv3)
Classifier: Operating System :: Unix
Classifier: Operating System :: Microsoft :: Windows
Classifier: Operating System :: MacOS
Classifier: Operating System :: Android
Classifier: Topic :: Internet
Classifier: Topic :: Security
Classifier: Development Status :: 5 - Production/Stable
Classifier: Intended Audience :: Developers
Classifier: Programming Language :: Python :: 3.6
Classifier: Programming Language :: Python :: 3.7
Classifier: Programming Language :: Python :: 3.8
Classifier: Programming Language :: Python :: 3.9
Classifier: Programming Language :: Python :: 3.10
Classifier: Programming Language :: Python :: 3.11
Classifier: Programming Language :: Python :: Implementation :: PyPy
Requires-Python: >=3.6
License-File: LICENSE
